pydevto/__init__.py
pydevto/markdown_converter.py
pydevto/markdownify_license.txt
pydevto/pydevto.py
pydevto-0.1.5.dist-info/LICENSE
pydevto-0.1.5.dist-info/WHEEL
pydevto-0.1.5.dist-info/METADATA
pydevto-0.1.5.dist-info/RECORD
