Metadata-Version: 2.1
Name: pydevto
Version: 0.1.5
Summary: Unofficial dev.to api for python
Home-page: https://github.com/lpellis/pydevto
License: MIT
Author: 'Loftie
Author-email: lpellis@gmail.com
Requires-Python: >=3.6,<4.0
Classifier: License :: OSI Approved :: MIT License
Classifier: Programming Language :: Python :: 3
Classifier: Programming Language :: Python :: 3.6
Classifier: Programming Language :: Python :: 3.7
Requires-Dist: beautifulsoup4 (>=4.8,<5.0)
Requires-Dist: requests (>=2.22,<3.0)
Requires-Dist: six (>=1.12,<2.0)
Project-URL: Repository, https://github.com/lpellis/pydevto
